libxb/__init__.py
libxb/__main__.py
libxb/driver.py
libxb/archives/common.py
libxb/archives/implement.py
libxb/archives/presets.py
libxb/core/cli.py
libxb/core/compress.py
libxb/core/exceptions.py
libxb/core/streams.py
libxb/core/utils.py
libxb-1.0.0.dist-info/METADATA
libxb-1.0.0.dist-info/WHEEL
libxb-1.0.0.dist-info/entry_points.txt
libxb-1.0.0.dist-info/licenses/LICENSE
libxb-1.0.0.dist-info/RECORD
