Metadata-Version: 2.4
Name: libxb
Version: 1.0.0
Summary: A library for the ClapHanz XB archive format
Project-URL: Homepage, https://github.com/kiwi515/libxb
Project-URL: Issues, https://github.com/kiwi515/libxb/issues
Author: Kiwi
License-Expression: MIT
License-File: LICENSE
Classifier: Development Status :: 4 - Beta
Classifier: Operating System :: OS Independent
Classifier: Programming Language :: Python :: 3
Classifier: Topic :: File Formats
Classifier: Topic :: Software Development :: Libraries
Requires-Python: >=3.10
